googleAPI/__init__.py
googleAPI/_version.py
googleAPI/credential.py
googleAPI/drive.py
googleAPI/gmail.py
googleAPI/sheet.py
googleAPI-0.1.0.dist-info/LICENSE
googleAPI-0.1.0.dist-info/METADATA
googleAPI-0.1.0.dist-info/WHEEL
googleAPI-0.1.0.dist-info/top_level.txt
googleAPI-0.1.0.dist-info/RECORD
