Metadata-Version: 2.1
Name: googleAPI
Version: 0.1.0
Summary: A high-level python interface to Google APIs
Home-page: https://github.com/zy2327/googleAPI
Author: Zeyu Yang
Author-email: zy2327@columbia.edu
License: UNKNOWN
Platform: UNKNOWN
Classifier: Programming Language :: Python :: 3
Classifier: License :: OSI Approved :: MIT License
Classifier: Operating System :: OS Independent
Requires-Python: >=3.6
